[{"client_msg_id":"3c55a21e-cd4f-465d-949e-b542b66cb4b6","type":"message","text":"where is Julia installed in the Windows runner?  I'm trying to debug an action with tmate, but I have no clue about how to run Julia in it","user":"UDB26738Q","ts":"1609351169.473800","team":"T68168MUP","blocks":[{"type":"rich_text","block_id":"rbo","elements":[{"type":"rich_text_section","elements":[{"type":"text","text":"where is Julia installed in the Windows runner?  I'm trying to debug an action with tmate, but I have no clue about how to run Julia in it"}]}]}],"thread_ts":"1609351169.473800","reply_count":29,"reply_users_count":3,"latest_reply":"1609363513.480300","reply_users":["U6NFPDBV1","UDB26738Q","U6C5KSWAC"],"subscribed":false},{"client_msg_id":"5975b00e-6b8b-4109-a24a-8175dc77838f","type":"message","text":"Would `where` help? <https://docs.microsoft.com/en-us/windows-server/administration/windows-commands/where>","user":"U6NFPDBV1","ts":"1609351403.473900","team":"T68168MUP","attachments":[{"title":"where","title_link":"https://docs.microsoft.com/en-us/windows-server/administration/windows-commands/where","text":"Reference article for where, which displays the location of files that match the given search pattern.","fallback":"where","thumb_url":"https://docs.microsoft.com/en-us/media/logos/logo-ms-social.png","from_url":"https://docs.microsoft.com/en-us/windows-server/administration/windows-commands/where","thumb_width":400,"thumb_height":400,"service_icon":"https://docs.microsoft.com/favicon.ico","service_name":"docs.microsoft.com","id":1,"original_url":"https://docs.microsoft.com/en-us/windows-server/administration/windows-commands/where"}],"blocks":[{"type":"rich_text","block_id":"2Cm","elements":[{"type":"rich_text_section","elements":[{"type":"text","text":"Would "},{"type":"text","text":"where","style":{"code":true}},{"type":"text","text":" help? "},{"type":"link","url":"https://docs.microsoft.com/en-us/windows-server/administration/windows-commands/where"}]}]}],"thread_ts":"1609351169.473800","parent_user_id":"UDB26738Q"},{"client_msg_id":"d4fe2e5a-6f62-4256-8564-e9b6c00c6c44","type":"message","text":"it's a `bash` (gitbash?) session, `find / -name \"*julia*\"` doesn't help much","user":"UDB26738Q","ts":"1609351451.474200","team":"T68168MUP","blocks":[{"type":"rich_text","block_id":"=c=D","elements":[{"type":"rich_text_section","elements":[{"type":"text","text":"it's a "},{"type":"text","text":"bash","style":{"code":true}},{"type":"text","text":" (gitbash?) session, "},{"type":"text","text":"find / -name \"*julia*\"","style":{"code":true}},{"type":"text","text":" doesn't help much"}]}]}],"thread_ts":"1609351169.473800","parent_user_id":"UDB26738Q"},{"client_msg_id":"31917f78-288f-4350-9083-2bcb2e472dc8","type":"message","text":"Does it not have `which` then?","user":"U6NFPDBV1","ts":"1609351670.474400","team":"T68168MUP","blocks":[{"type":"rich_text","block_id":"JKr3s","elements":[{"type":"rich_text_section","elements":[{"type":"text","text":"Does it not have "},{"type":"text","text":"which","style":{"code":true}},{"type":"text","text":" then?"}]}]}],"thread_ts":"1609351169.473800","parent_user_id":"UDB26738Q"},{"client_msg_id":"41391569-6fe0-46db-bc18-912cfed1272d","type":"message","text":"Oh wait that wouldn't work since it's not on the PATH","user":"U6NFPDBV1","ts":"1609351691.474600","team":"T68168MUP","blocks":[{"type":"rich_text","block_id":"XFI","elements":[{"type":"rich_text_section","elements":[{"type":"text","text":"Oh wait that wouldn't work since it's not on the PATH"}]}]}],"thread_ts":"1609351169.473800","parent_user_id":"UDB26738Q"},{"client_msg_id":"c755caec-272d-4f2b-a94a-21cc0f57ee42","type":"message","text":"it does have `which`, but it wouldn't help much: I don't know how to start julia","user":"UDB26738Q","ts":"1609351698.474800","team":"T68168MUP","blocks":[{"type":"rich_text","block_id":"tFAH","elements":[{"type":"rich_text_section","elements":[{"type":"text","text":"it does have "},{"type":"text","text":"which","style":{"code":true}},{"type":"text","text":", but it wouldn't help much: I don't know how to start julia"}]}]}],"thread_ts":"1609351169.473800","parent_user_id":"UDB26738Q"},{"client_msg_id":"460837f7-2416-4457-bd57-5be8d63d7156","type":"message","text":"I guess I could download it again, but it should be already somewhere around","user":"UDB26738Q","ts":"1609351737.475000","team":"T68168MUP","blocks":[{"type":"rich_text","block_id":"DYyT","elements":[{"type":"rich_text_section","elements":[{"type":"text","text":"I guess I could download it again, but it should be already somewhere around"}]}]}],"thread_ts":"1609351169.473800","parent_user_id":"UDB26738Q"},{"client_msg_id":"82d0ccfd-3b15-48c8-a973-8fc9432e9082","type":"message","text":"<https://github.com/actions/virtual-environments/blob/main/images/win/scripts/Installers/Install-Julia.ps1> seems to be installed via chocolatey","user":"U6NFPDBV1","ts":"1609351744.475200","team":"T68168MUP","edited":{"user":"U6NFPDBV1","ts":"1609351749.000000"},"blocks":[{"type":"rich_text","block_id":"wu1tU","elements":[{"type":"rich_text_section","elements":[{"type":"link","url":"https://github.com/actions/virtual-environments/blob/main/images/win/scripts/Installers/Install-Julia.ps1"},{"type":"text","text":" seems to be installed via chocolatey"}]}]}],"thread_ts":"1609351169.473800","parent_user_id":"UDB26738Q"},{"client_msg_id":"9e5473c0-33bb-43b2-a767-02a8b45c2000","type":"message","text":"try this? <https://github.com/actions/virtual-environments/blob/main/images/win/scripts/ImageHelpers/ChocoHelpers.ps1#L17>","user":"U6NFPDBV1","ts":"1609351785.475600","team":"T68168MUP","blocks":[{"type":"rich_text","block_id":"7bCJg","elements":[{"type":"rich_text_section","elements":[{"type":"text","text":"try this? "},{"type":"link","url":"https://github.com/actions/virtual-environments/blob/main/images/win/scripts/ImageHelpers/ChocoHelpers.ps1#L17"}]}]}],"thread_ts":"1609351169.473800","parent_user_id":"UDB26738Q"},{"client_msg_id":"5943cbe9-9c30-47dc-aceb-bbd5049fb929","type":"message","text":"no, I want the one installed by `setup-julia`","user":"UDB26738Q","ts":"1609351795.475800","team":"T68168MUP","blocks":[{"type":"rich_text","block_id":"bvwJK","elements":[{"type":"rich_text_section","elements":[{"type":"text","text":"no, I want the one installed by "},{"type":"text","text":"setup-julia","style":{"code":true}}]}]}],"thread_ts":"1609351169.473800","parent_user_id":"UDB26738Q"},{"client_msg_id":"aef77ed4-c17e-4f3a-8d2c-fe834ff86df9","type":"message","text":"I want to test the nightly","user":"UDB26738Q","ts":"1609351804.476000","team":"T68168MUP","blocks":[{"type":"rich_text","block_id":"y0tL","elements":[{"type":"rich_text_section","elements":[{"type":"text","text":"I want to test the nightly"}]}]}],"thread_ts":"1609351169.473800","parent_user_id":"UDB26738Q"},{"client_msg_id":"544fcde9-8abf-424e-aaf6-9f4853d94e2e","type":"message","text":"Oh woops","user":"U6NFPDBV1","ts":"1609351805.476200","team":"T68168MUP","blocks":[{"type":"rich_text","block_id":"S3Z1Y","elements":[{"type":"rich_text_section","elements":[{"type":"text","text":"Oh woops"}]}]}],"thread_ts":"1609351169.473800","parent_user_id":"UDB26738Q"},{"client_msg_id":"b99e56dd-c414-4876-a491-aab4894dd97d","type":"message","text":"for the record, there is `/c/Julia/bin/julia.exe`, but if I try to run it, it hangs","user":"UDB26738Q","ts":"1609351859.476400","team":"T68168MUP","edited":{"user":"UDB26738Q","ts":"1609351884.000000"},"blocks":[{"type":"rich_text","block_id":"LZ3I9","elements":[{"type":"rich_text_section","elements":[{"type":"text","text":"for the record, there is "},{"type":"text","text":"/c/Julia/bin/julia.exe","style":{"code":true}},{"type":"text","text":", but if I try to run it, it hangs"}]}]}],"thread_ts":"1609351169.473800","parent_user_id":"UDB26738Q"},{"client_msg_id":"08b733b3-9f34-4be3-80ec-83b99b592b2a","type":"message","text":"hold on, it's just _slow_","user":"UDB26738Q","ts":"1609351869.476600","team":"T68168MUP","blocks":[{"type":"rich_text","block_id":"EfI","elements":[{"type":"rich_text_section","elements":[{"type":"text","text":"hold on, it's just "},{"type":"text","text":"slow","style":{"italic":true}}]}]}],"thread_ts":"1609351169.473800","parent_user_id":"UDB26738Q","reactions":[{"name":"slow_parrot","users":["UN97XTLCV","U7THT3TM3"],"count":2}]},{"client_msg_id":"6b06a0eb-9d94-4359-86c2-9cc26541a095","type":"message","text":"good, so now I know how to run the Julia installed by GitHub, I just need to find the one installed by the action :sweat_smile:","user":"UDB26738Q","ts":"1609351922.476900","team":"T68168MUP","blocks":[{"type":"rich_text","block_id":"6t4","elements":[{"type":"rich_text_section","elements":[{"type":"text","text":"good, so now I know how to run the Julia installed by GitHub, I just need to find the one installed by the action "},{"type":"emoji","name":"sweat_smile"}]}]}],"thread_ts":"1609351169.473800","parent_user_id":"UDB26738Q"},{"client_msg_id":"1ad6dadd-9932-4cbf-8d08-85ad59951db5","type":"message","text":"<https://github.com/julia-actions/setup-julia/blob/master/src/installer.ts#L142>","user":"U6NFPDBV1","ts":"1609351926.477100","team":"T68168MUP","blocks":[{"type":"rich_text","block_id":"=FGl","elements":[{"type":"rich_text_section","elements":[{"type":"link","url":"https://github.com/julia-actions/setup-julia/blob/master/src/installer.ts#L142"}]}]}],"thread_ts":"1609351169.473800","parent_user_id":"UDB26738Q"},{"client_msg_id":"3ba1ae1f-b77b-4166-b2fd-8634bd9a732d","type":"message","text":"Now to find what `@actions/tool-cache` does","user":"U6NFPDBV1","ts":"1609351934.477300","team":"T68168MUP","blocks":[{"type":"rich_text","block_id":"+mH","elements":[{"type":"rich_text_section","elements":[{"type":"text","text":"Now to find what "},{"type":"text","text":"@actions/tool-cache","style":{"code":true}},{"type":"text","text":" does"}]}]}],"thread_ts":"1609351169.473800","parent_user_id":"UDB26738Q"},{"client_msg_id":"ed028612-98bc-45e4-8847-4b4c9a4d26ab","type":"message","text":"the step shows <https://github.com/giordano/FFTW.jl/runs/1627205197?check_suite_focus=true#step:3:10>\n```powershell -Command \"Start-Process -FilePath D:\\a\\_temp\\47afc347-0f07-407c-aa20-08c9ec164261 -ArgumentList \\\"/SILENT /dir=D:\\a\\FFTW.jl\\FFTW.jl\\julia-x64-nightly-lCzux1\\\" -NoNewWindow -Wait\"```","user":"UDB26738Q","ts":"1609351961.477500","team":"T68168MUP","blocks":[{"type":"rich_text","block_id":"OKe","elements":[{"type":"rich_text_section","elements":[{"type":"text","text":"the step shows "},{"type":"link","url":"https://github.com/giordano/FFTW.jl/runs/1627205197?check_suite_focus=true#step:3:10"},{"type":"text","text":"\n"}]},{"type":"rich_text_preformatted","elements":[{"type":"text","text":"powershell -Command \"Start-Process -FilePath D:\\a\\_temp\\47afc347-0f07-407c-aa20-08c9ec164261 -ArgumentList \\\"/SILENT /dir=D:\\a\\FFTW.jl\\FFTW.jl\\julia-x64-nightly-lCzux1\\\" -NoNewWindow -Wait\""}]}]}],"thread_ts":"1609351169.473800","parent_user_id":"UDB26738Q"},{"client_msg_id":"f977286b-e083-4bec-ae1f-5cefa91bb469","type":"message","text":"but there is no `julia-x64-nightly-*` in the FFTW directory","user":"UDB26738Q","ts":"1609351994.477700","team":"T68168MUP","blocks":[{"type":"rich_text","block_id":"6ao","elements":[{"type":"rich_text_section","elements":[{"type":"text","text":"but there is no "},{"type":"text","text":"julia-x64-nightly-*","style":{"code":true}},{"type":"text","text":" in the FFTW directory"}]}]}],"thread_ts":"1609351169.473800","parent_user_id":"UDB26738Q"},{"client_msg_id":"c78c0e17-969f-4107-8f3d-b757e72f4918","type":"message","text":"That makes sense <https://github.com/actions/toolkit/blob/main/packages/tool-cache/src/tool-cache.ts#L42>","user":"U6NFPDBV1","ts":"1609351994.477900","team":"T68168MUP","blocks":[{"type":"rich_text","block_id":"nkg","elements":[{"type":"rich_text_section","elements":[{"type":"text","text":"That makes sense "},{"type":"link","url":"https://github.com/actions/toolkit/blob/main/packages/tool-cache/src/tool-cache.ts#L42"}]}]}],"thread_ts":"1609351169.473800","parent_user_id":"UDB26738Q"},{"client_msg_id":"bb650519-c460-4c23-9eff-69c4ce514f11","type":"message","text":"Is `RUNNER_TEMP` defined? <https://github.com/actions/toolkit/blob/c861dd8859fe5294289fcada363ce9bc71e9d260/packages/tool-cache/src/tool-cache.ts#L701>","user":"U6NFPDBV1","ts":"1609352029.478100","team":"T68168MUP","blocks":[{"type":"rich_text","block_id":"4bo/=","elements":[{"type":"rich_text_section","elements":[{"type":"text","text":"Is "},{"type":"text","text":"RUNNER_TEMP","style":{"code":true}},{"type":"text","text":" defined? "},{"type":"link","url":"https://github.com/actions/toolkit/blob/c861dd8859fe5294289fcada363ce9bc71e9d260/packages/tool-cache/src/tool-cache.ts#L701"}]}]}],"thread_ts":"1609351169.473800","parent_user_id":"UDB26738Q"},{"client_msg_id":"6df27879-7865-42fe-af51-2bed872c3776","type":"message","text":"nope","user":"UDB26738Q","ts":"1609352046.478300","team":"T68168MUP","blocks":[{"type":"rich_text","block_id":"VpiO","elements":[{"type":"rich_text_section","elements":[{"type":"text","text":"nope"}]}]}],"thread_ts":"1609351169.473800","parent_user_id":"UDB26738Q"},{"client_msg_id":"ad479de6-d27c-479c-84e1-086324c58088","type":"message","text":"Hm, maybe try enabling debug logs, since it should be printed <https://github.com/actions/toolkit/blob/main/packages/tool-cache/src/tool-cache.ts#L45>","user":"U6NFPDBV1","ts":"1609352064.478500","team":"T68168MUP","blocks":[{"type":"rich_text","block_id":"jM4w","elements":[{"type":"rich_text_section","elements":[{"type":"text","text":"Hm, maybe try enabling debug logs, since it should be printed "},{"type":"link","url":"https://github.com/actions/toolkit/blob/main/packages/tool-cache/src/tool-cache.ts#L45"}]}]}],"thread_ts":"1609351169.473800","parent_user_id":"UDB26738Q"},{"client_msg_id":"ad24be85-d505-4a63-89fb-f941d07e9625","type":"message","text":"Oh wait that won't help very much, since that's just the tarball and it doesn't really tell you the final install location","user":"U6NFPDBV1","ts":"1609352188.478700","team":"T68168MUP","blocks":[{"type":"rich_text","block_id":"YQ3ep","elements":[{"type":"rich_text_section","elements":[{"type":"text","text":"Oh wait that won't help very much, since that's just the tarball and it doesn't really tell you the final install location"}]}]}],"thread_ts":"1609351169.473800","parent_user_id":"UDB26738Q"},{"client_msg_id":"26f18d13-858b-44f0-bae6-532641267641","type":"message","text":"This is more promising <https://github.com/julia-actions/setup-julia/blob/master/src/installer.ts#L155>","user":"U6NFPDBV1","ts":"1609352217.478900","team":"T68168MUP","blocks":[{"type":"rich_text","block_id":"CsV","elements":[{"type":"rich_text_section","elements":[{"type":"text","text":"This is more promising "},{"type":"link","url":"https://github.com/julia-actions/setup-julia/blob/master/src/installer.ts#L155"}]}]}],"thread_ts":"1609351169.473800","parent_user_id":"UDB26738Q"},{"client_msg_id":"db9a79f2-1e28-464b-b8ef-2099acb9ee50","type":"message","text":"looks like it should be the path in <https://julialang.slack.com/archives/CPWJ5DGG1/p1609351961477500?thread_ts=1609351169.473800&amp;cid=CPWJ5DGG1>","user":"UDB26738Q","ts":"1609352282.479100","team":"T68168MUP","attachments":[{"from_url":"https://julialang.slack.com/archives/CPWJ5DGG1/p1609351961477500?thread_ts=1609351169.473800&amp;cid=CPWJ5DGG1","fallback":"[December 30th, 2020 10:12 AM] mose: the step shows <https://github.com/giordano/FFTW.jl/runs/1627205197?check_suite_focus=true#step:3:10>\n```powershell -Command \"Start-Process -FilePath D:\\a\\_temp\\47afc347-0f07-407c-aa20-08c9ec164261 -ArgumentList \\\"/SILENT /dir=D:\\a\\FFTW.jl\\FFTW.jl\\julia-x64-nightly-lCzux1\\\" -NoNewWindow -Wait\"```","ts":"1609351961.477500","author_id":"UDB26738Q","author_subname":"Mosè Giordano","channel_id":"CPWJ5DGG1","channel_name":"github-actions","is_msg_unfurl":true,"is_reply_unfurl":true,"text":"the step shows <https://github.com/giordano/FFTW.jl/runs/1627205197?check_suite_focus=true#step:3:10>\n```powershell -Command \"Start-Process -FilePath D:\\a\\_temp\\47afc347-0f07-407c-aa20-08c9ec164261 -ArgumentList \\\"/SILENT /dir=D:\\a\\FFTW.jl\\FFTW.jl\\julia-x64-nightly-lCzux1\\\" -NoNewWindow -Wait\"```","author_name":"Mosè Giordano","author_link":"https://julialang.slack.com/team/UDB26738Q","author_icon":"https://secure.gravatar.com/avatar/b1b9938790729d96af6f168d8ce0f917.jpg?s=48&d=https%3A%2F%2Fa.slack-edge.com%2Fdf10d%2Fimg%2Favatars%2Fava_0024-48.png","mrkdwn_in":["text"],"id":1,"original_url":"https://julialang.slack.com/archives/CPWJ5DGG1/p1609351961477500?thread_ts=1609351169.473800&amp;cid=CPWJ5DGG1","footer":"From a thread in #github-actions"}],"blocks":[{"type":"rich_text","block_id":"aXxo7","elements":[{"type":"rich_text_section","elements":[{"type":"text","text":"looks like it should be the path in "},{"type":"link","url":"https://julialang.slack.com/archives/CPWJ5DGG1/p1609351961477500?thread_ts=1609351169.473800&cid=CPWJ5DGG1"}]}]}],"thread_ts":"1609351169.473800","parent_user_id":"UDB26738Q"},{"client_msg_id":"e503cd2d-0492-4a70-a371-238ae43b412b","type":"message","text":"but\n```runneradmin@fv-az153-614 MINGW64 /d/a/FFTW.jl/FFTW.jl\n# ls -a\n.   .drone.jsonnet  .git            .github     CITATION.bib  docs     Manifest.toml  README.md  test\n..  .drone.yml      .gitattributes  .gitignore  deps          LICENSE  Project.toml   src```","user":"UDB26738Q","ts":"1609352322.479400","team":"T68168MUP","blocks":[{"type":"rich_text","block_id":"bny2","elements":[{"type":"rich_text_section","elements":[{"type":"text","text":"but\n"}]},{"type":"rich_text_preformatted","elements":[{"type":"text","text":"runneradmin@fv-az153-614 MINGW64 /d/a/FFTW.jl/FFTW.jl\n# ls -a\n.   .drone.jsonnet  .git            .github     CITATION.bib  docs     Manifest.toml  README.md  test\n..  .drone.yml      .gitattributes  .gitignore  deps          LICENSE  Project.toml   src"}]}]}],"thread_ts":"1609351169.473800","parent_user_id":"UDB26738Q"},{"client_msg_id":"5f552533-345c-42b9-b88e-5f999d4b2241","type":"message","text":"well, I ended up downloading the portable package from <https://julialang.org/downloads/nightlies/>","user":"UDB26738Q","ts":"1609352681.479600","team":"T68168MUP","edited":{"user":"UDB26738Q","ts":"1609352686.000000"},"blocks":[{"type":"rich_text","block_id":"nbKL","elements":[{"type":"rich_text_section","elements":[{"type":"text","text":"well, I ended up downloading the portable package from "},{"type":"link","url":"https://julialang.org/downloads/nightlies/"}]}]}],"thread_ts":"1609351169.473800","parent_user_id":"UDB26738Q"},{"client_msg_id":"df9e9b9d-d605-45ba-887c-f29dfd4d0f61","type":"message","text":"&gt; Hm, maybe try enabling debug logs, since it should be printed\nYea debug logs print it. Should be in `C:\\hostedtoolcache\\windows\\julia\\nightly\\x64`","user":"U6C5KSWAC","ts":"1609363504.480100","team":"T68168MUP","blocks":[{"type":"rich_text","block_id":"4AH","elements":[{"type":"rich_text_quote","elements":[{"type":"text","text":"Hm, maybe try enabling debug logs, since it should be printed"}]},{"type":"rich_text_section","elements":[{"type":"text","text":"\nYea debug logs print it. Should be in "},{"type":"text","text":"C:\\hostedtoolcache\\windows\\julia\\nightly\\x64","style":{"code":true}}]}]}],"thread_ts":"1609351169.473800","parent_user_id":"UDB26738Q","reactions":[{"name":"+1","users":["U7THT3TM3"],"count":1}]},{"client_msg_id":"8d357c53-e23d-4c73-8b0d-8304a550da81","type":"message","text":"You can also use the `julia-bindir` output","user":"U6C5KSWAC","ts":"1609363513.480300","team":"T68168MUP","blocks":[{"type":"rich_text","block_id":"I9H","elements":[{"type":"rich_text_section","elements":[{"type":"text","text":"You can also use the "},{"type":"text","text":"julia-bindir","style":{"code":true}},{"type":"text","text":" output"}]}]}],"thread_ts":"1609351169.473800","parent_user_id":"UDB26738Q","reactions":[{"name":"+1","users":["U7THT3TM3"],"count":1}]}]