[{"client_msg_id":"6c421a21-c038-4811-ad5b-bf5e1e78fba6","type":"message","text":"Is there a way to start Julia w/ and empty environment stack? I am doing a \"julia basics\" tutorial this afternoon and want to be able to demo from a clean slate","user":"UP95S4864","ts":"1613134723.474100","team":"T68168MUP","blocks":[{"type":"rich_text","block_id":"4WQZ","elements":[{"type":"rich_text_section","elements":[{"type":"text","text":"Is there a way to start Julia w/ and empty environment stack? I am doing a \"julia basics\" tutorial this afternoon and want to be able to demo from a clean slate"}]}]}],"thread_ts":"1613134723.474100","reply_count":6,"reply_users_count":3,"latest_reply":"1613136089.475500","reply_users":["UH8A351DJ","UDB26738Q","UP95S4864"],"subscribed":false},{"client_msg_id":"1f18c364-d87e-49a3-9b37-a327c86c5f45","type":"message","text":"`--startup-file=no`","user":"UH8A351DJ","ts":"1613134787.474200","team":"T68168MUP","blocks":[{"type":"rich_text","block_id":"ncL","elements":[{"type":"rich_text_section","elements":[{"type":"text","text":"--startup-file=no","style":{"code":true}}]}]}],"thread_ts":"1613134723.474100","parent_user_id":"UP95S4864"},{"client_msg_id":"206b549f-d981-42fd-9710-f76858d741c9","type":"message","text":"`JULIA_LOAD_PATH=\"\"`: <https://docs.julialang.org/en/v1/manual/environment-variables/#JULIA_LOAD_PATH>","user":"UDB26738Q","ts":"1613134818.474400","team":"T68168MUP","edited":{"user":"UDB26738Q","ts":"1613134900.000000"},"blocks":[{"type":"rich_text","block_id":"d3Frg","elements":[{"type":"rich_text_section","elements":[{"type":"text","text":"JULIA_LOAD_PATH=\"\"","style":{"code":true}},{"type":"text","text":": "},{"type":"link","url":"https://docs.julialang.org/en/v1/manual/environment-variables/#JULIA_LOAD_PATH"}]}]}],"thread_ts":"1613134723.474100","parent_user_id":"UP95S4864","reactions":[{"name":"heavy_check_mark","users":["UH8A351DJ"],"count":1},{"name":"point_up","users":["U6A936746"],"count":1}]},{"client_msg_id":"0eb43617-316e-4db2-ac44-5b9cc0f78f71","type":"message","text":"If I do this, where will subsequently added packages get recorded?","user":"UP95S4864","ts":"1613134977.474800","team":"T68168MUP","blocks":[{"type":"rich_text","block_id":"rhT","elements":[{"type":"rich_text_section","elements":[{"type":"text","text":"If I do this, where will subsequently added packages get recorded?"}]}]}],"thread_ts":"1613134723.474100","parent_user_id":"UP95S4864"},{"client_msg_id":"54d91a4f-964a-41c4-8706-22adc537990a","type":"message","text":"you can do something like\n```export JULIA_LOAD_PATH=\njulia --project=my-environment```","user":"UDB26738Q","ts":"1613135011.475000","team":"T68168MUP","edited":{"user":"UDB26738Q","ts":"1613135023.000000"},"blocks":[{"type":"rich_text","block_id":"7Bwl","elements":[{"type":"rich_text_section","elements":[{"type":"text","text":"you can do something like\n"}]},{"type":"rich_text_preformatted","elements":[{"type":"text","text":"export JULIA_LOAD_PATH=\njulia --project=my-environment"}]}]}],"thread_ts":"1613134723.474100","parent_user_id":"UP95S4864"},{"client_msg_id":"b679de29-bb02-4261-9d74-da882c7575ce","type":"message","text":"honestly I'm not sure whether the right value is `\"\"` or `@`, maybe the latter","user":"UDB26738Q","ts":"1613135046.475300","team":"T68168MUP","blocks":[{"type":"rich_text","block_id":"AcZ","elements":[{"type":"rich_text_section","elements":[{"type":"text","text":"honestly I'm not sure whether the right value is "},{"type":"text","text":"\"\"","style":{"code":true}},{"type":"text","text":" or "},{"type":"text","text":"@","style":{"code":true}},{"type":"text","text":", maybe the latter"}]}]}],"thread_ts":"1613134723.474100","parent_user_id":"UP95S4864"},{"client_msg_id":"cb207f7e-ff7d-40dd-b61b-3074d5fb7564","type":"message","text":"Thanks, this is a huge help","user":"UP95S4864","ts":"1613136089.475500","team":"T68168MUP","blocks":[{"type":"rich_text","block_id":"R0/e5","elements":[{"type":"rich_text_section","elements":[{"type":"text","text":"Thanks, this is a huge help"}]}]}],"thread_ts":"1613134723.474100","parent_user_id":"UP95S4864"}]