[{"client_msg_id":"ed720eca-fb28-4522-b397-0ff1860cc3c0","type":"message","text":"Do you remember who was playing with “boids”, swarms and love and hate? Was this actually here or did it just go over say hacker-news?","user":"U6C937ENB","ts":"1615209954.129300","team":"T68168MUP","blocks":[{"type":"rich_text","block_id":"CUcb","elements":[{"type":"rich_text_section","elements":[{"type":"text","text":"Do you remember who was playing with “boids”, swarms and love and hate? Was this actually here or did it just go over say hacker-news?"}]}]}],"thread_ts":"1615209954.129300","reply_count":17,"reply_users_count":4,"latest_reply":"1615876449.007700","reply_users":["U6BNE7LTZ","U6C937ENB","UH24GRBLL","U90JR0C80"],"subscribed":false},{"client_msg_id":"38af373d-97f3-44c1-8c9e-5072a57ba7e9","type":"message","text":"<https://www.youtube.com/watch?v=8gS6wejsGsY> ?","user":"U6BNE7LTZ","ts":"1615210025.129400","team":"T68168MUP","attachments":[{"service_name":"YouTube","service_url":"https://www.youtube.com/","title":"JuliaCon 2020 | Boids: Dancing with Friends and Enemies | Jesse Bettencourt","title_link":"https://www.youtube.com/watch?v=8gS6wejsGsY","author_name":"The Julia Programming Language","author_link":"https://www.youtube.com/user/JuliaLanguage","thumb_url":"https://i.ytimg.com/vi/8gS6wejsGsY/hqdefault.jpg","thumb_width":480,"thumb_height":360,"fallback":"YouTube Video: JuliaCon 2020 | Boids: Dancing with Friends and Enemies | Jesse Bettencourt","video_html":"<iframe width=\"400\" height=\"225\" src=\"https://www.youtube.com/embed/8gS6wejsGsY?feature=oembed&autoplay=1&iv_load_policy=3\" frameborder=\"0\" allow=\"accelerometer; autoplay; clipboard-write; encrypted-media; gyroscope; picture-in-picture\" allowfullscreen></iframe>","video_html_width":400,"video_html_height":225,"from_url":"https://www.youtube.com/watch?v=8gS6wejsGsY","service_icon":"https://a.slack-edge.com/80588/img/unfurl_icons/youtube.png","id":1,"original_url":"https://www.youtube.com/watch?v=8gS6wejsGsY"}],"blocks":[{"type":"rich_text","block_id":"MuHaA","elements":[{"type":"rich_text_section","elements":[{"type":"link","url":"https://www.youtube.com/watch?v=8gS6wejsGsY"},{"type":"text","text":" ?"}]}]}],"thread_ts":"1615209954.129300","parent_user_id":"U6C937ENB"},{"client_msg_id":"71657f2f-2f8e-4cc4-a482-5176a995f124","type":"message","text":"Thank you!","user":"U6C937ENB","ts":"1615210045.129700","team":"T68168MUP","blocks":[{"type":"rich_text","block_id":"O0=cY","elements":[{"type":"rich_text_section","elements":[{"type":"text","text":"Thank you!"}]}]}],"thread_ts":"1615209954.129300","parent_user_id":"U6C937ENB"},{"client_msg_id":"c30e8cbd-f13a-495b-bd68-4efa7e297c92","type":"message","text":"Does youtube export bibtex?","user":"U6C937ENB","ts":"1615210075.129900","team":"T68168MUP","blocks":[{"type":"rich_text","block_id":"1Wu8P","elements":[{"type":"rich_text_section","elements":[{"type":"text","text":"Does youtube export bibtex?"}]}]}],"thread_ts":"1615209954.129300","parent_user_id":"U6C937ENB","reactions":[{"name":"shrugging","users":["U6BNE7LTZ"],"count":1}]},{"type":"message","text":":slightly_smiling_face: <@U90JR0C80>","files":[{"id":"F01R76A57EU","created":1615211158,"timestamp":1615211158,"name":"Screenshot 2021-03-08 at 14.45.35.png","title":"Screenshot 2021-03-08 at 14.45.35.png","mimetype":"image/png","filetype":"png","pretty_type":"PNG","user":"U6C937ENB","editable":false,"size":130562,"mode":"hosted","is_external":false,"external_type":"","is_public":true,"public_url_shared":false,"display_as_bot":false,"username":"","url_private":"https://files.slack.com/files-pri/T68168MUP-F01R76A57EU/screenshot_2021-03-08_at_14.45.35.png","url_private_download":"https://files.slack.com/files-pri/T68168MUP-F01R76A57EU/download/screenshot_2021-03-08_at_14.45.35.png","thumb_64":"https://files.slack.com/files-tmb/T68168MUP-F01R76A57EU-9e9134e6d8/screenshot_2021-03-08_at_14.45.35_64.png","thumb_80":"https://files.slack.com/files-tmb/T68168MUP-F01R76A57EU-9e9134e6d8/screenshot_2021-03-08_at_14.45.35_80.png","thumb_360":"https://files.slack.com/files-tmb/T68168MUP-F01R76A57EU-9e9134e6d8/screenshot_2021-03-08_at_14.45.35_360.png","thumb_360_w":360,"thumb_360_h":78,"thumb_480":"https://files.slack.com/files-tmb/T68168MUP-F01R76A57EU-9e9134e6d8/screenshot_2021-03-08_at_14.45.35_480.png","thumb_480_w":480,"thumb_480_h":104,"thumb_160":"https://files.slack.com/files-tmb/T68168MUP-F01R76A57EU-9e9134e6d8/screenshot_2021-03-08_at_14.45.35_160.png","thumb_720":"https://files.slack.com/files-tmb/T68168MUP-F01R76A57EU-9e9134e6d8/screenshot_2021-03-08_at_14.45.35_720.png","thumb_720_w":720,"thumb_720_h":156,"thumb_800":"https://files.slack.com/files-tmb/T68168MUP-F01R76A57EU-9e9134e6d8/screenshot_2021-03-08_at_14.45.35_800.png","thumb_800_w":800,"thumb_800_h":173,"thumb_960":"https://files.slack.com/files-tmb/T68168MUP-F01R76A57EU-9e9134e6d8/screenshot_2021-03-08_at_14.45.35_960.png","thumb_960_w":960,"thumb_960_h":208,"thumb_1024":"https://files.slack.com/files-tmb/T68168MUP-F01R76A57EU-9e9134e6d8/screenshot_2021-03-08_at_14.45.35_1024.png","thumb_1024_w":1024,"thumb_1024_h":222,"original_w":1858,"original_h":402,"thumb_tiny":"AwAKADDQ7mkp/elxQAzj3peP8inYowKAG0DrTsD0oxQB/9k=","permalink":"https://julialang.slack.com/files/U6C937ENB/F01R76A57EU/screenshot_2021-03-08_at_14.45.35.png","permalink_public":"https://slack-files.com/T68168MUP-F01R76A57EU-371cd0789f","is_starred":false,"has_rich_preview":false}],"upload":false,"blocks":[{"type":"rich_text","block_id":"LiTwa","elements":[{"type":"rich_text_section","elements":[{"type":"emoji","name":"slightly_smiling_face"},{"type":"text","text":" "},{"type":"user","user_id":"U90JR0C80"}]}]}],"user":"U6C937ENB","display_as_bot":false,"ts":"1615211172.130400","thread_ts":"1615209954.129300","parent_user_id":"U6C937ENB"},{"client_msg_id":"6834ab72-c046-4b99-842d-1deef1626b1e","type":"message","text":"I was always advised against doing that since the videos may vanish at any point","user":"UH24GRBLL","ts":"1615211312.130600","team":"T68168MUP","blocks":[{"type":"rich_text","block_id":"C5//u","elements":[{"type":"rich_text_section","elements":[{"type":"text","text":"I was always advised against doing that since the videos may vanish at any point"}]}]}],"thread_ts":"1615209954.129300","parent_user_id":"U6C937ENB"},{"client_msg_id":"24475f06-ad84-468b-947f-0da47f5d658f","type":"message","text":"y'know, youtube being youtube and all that","user":"UH24GRBLL","ts":"1615211325.130800","team":"T68168MUP","blocks":[{"type":"rich_text","block_id":"PfW","elements":[{"type":"rich_text_section","elements":[{"type":"text","text":"y'know, youtube being youtube and all that"}]}]}],"thread_ts":"1615209954.129300","parent_user_id":"U6C937ENB"},{"client_msg_id":"c8d51e59-6236-4797-8328-6d1a85846662","type":"message","text":"That doesn’t change that I used it","user":"U6C937ENB","ts":"1615211337.131000","team":"T68168MUP","blocks":[{"type":"rich_text","block_id":"WfCR","elements":[{"type":"rich_text_section","elements":[{"type":"text","text":"That doesn’t change that I used it"}]}]}],"thread_ts":"1615209954.129300","parent_user_id":"U6C937ENB"},{"client_msg_id":"2a2e0194-39fe-4e9b-9133-c63cb5bf9b8b","type":"message","text":"But you have a point of course","user":"U6C937ENB","ts":"1615211347.131200","team":"T68168MUP","blocks":[{"type":"rich_text","block_id":"VRCc","elements":[{"type":"rich_text_section","elements":[{"type":"text","text":"But you have a point of course"}]}]}],"thread_ts":"1615209954.129300","parent_user_id":"U6C937ENB"},{"client_msg_id":"8cd805a8-0153-4f74-ace6-25b4e1684acd","type":"message","text":"But I should say: Recording of a talk and not pin it to youtube perhaps","user":"U6C937ENB","ts":"1615211377.131400","team":"T68168MUP","blocks":[{"type":"rich_text","block_id":"2I1","elements":[{"type":"rich_text_section","elements":[{"type":"text","text":"But I should say: Recording of a talk and not pin it to youtube perhaps"}]}]}],"thread_ts":"1615209954.129300","parent_user_id":"U6C937ENB"},{"client_msg_id":"04017432-7b40-41a2-bf65-cd3c63629907","type":"message","text":"right","user":"UH24GRBLL","ts":"1615211582.131600","team":"T68168MUP","blocks":[{"type":"rich_text","block_id":"+9D/","elements":[{"type":"rich_text_section","elements":[{"type":"text","text":"right"}]}]}],"thread_ts":"1615209954.129300","parent_user_id":"U6C937ENB","reactions":[{"name":"+1","users":["U6C937ENB"],"count":1}]},{"client_msg_id":"dee6accd-0c25-400a-9024-393cfb4af975","type":"message","text":"it's super frustrating because sometimes the recording as a youtube video really is the best source to point people to","user":"UH24GRBLL","ts":"1615211604.131900","team":"T68168MUP","blocks":[{"type":"rich_text","block_id":"UQua","elements":[{"type":"rich_text_section","elements":[{"type":"text","text":"it's super frustrating because sometimes the recording as a youtube video really is the best source to point people to"}]}]}],"thread_ts":"1615209954.129300","parent_user_id":"U6C937ENB"},{"client_msg_id":"0360e65d-8bdf-4dd1-8283-c3da8c172ea3","type":"message","text":"I’ll put that in the URL field anyway","user":"U6C937ENB","ts":"1615211631.132100","team":"T68168MUP","blocks":[{"type":"rich_text","block_id":"AbFJ","elements":[{"type":"rich_text_section","elements":[{"type":"text","text":"I’ll put that in the URL field anyway"}]}]}],"thread_ts":"1615209954.129300","parent_user_id":"U6C937ENB"},{"client_msg_id":"0511e502-a311-437a-b8fa-6bb642e14a4d","type":"message","text":"… if I figure out how to display it with biblatex…","user":"U6C937ENB","ts":"1615211646.132300","team":"T68168MUP","blocks":[{"type":"rich_text","block_id":"vqJgU","elements":[{"type":"rich_text_section","elements":[{"type":"text","text":"… if I figure out how to display it with biblatex…"}]}]}],"thread_ts":"1615209954.129300","parent_user_id":"U6C937ENB"},{"client_msg_id":"E327E1C3-4892-4462-A8B4-D4FFFDEB3C85","type":"message","text":"Ooo <@U6C937ENB> what are you up to?","user":"U90JR0C80","ts":"1615214304.134300","team":"T68168MUP","blocks":[{"type":"rich_text","block_id":"=HL","elements":[{"type":"rich_text_section","elements":[{"type":"text","text":"Ooo "},{"type":"user","user_id":"U6C937ENB"},{"type":"text","text":" what are you up to?"}]}]}],"thread_ts":"1615209954.129300","parent_user_id":"U6C937ENB"},{"client_msg_id":"6cebe3e4-cd07-4276-97c4-daab5e4965db","type":"message","text":"I saw a swarm of boids and wanted to know who is actually in love with whom!","user":"U6C937ENB","ts":"1615218810.136700","team":"T68168MUP","blocks":[{"type":"rich_text","block_id":"iubf","elements":[{"type":"rich_text_section","elements":[{"type":"text","text":"I saw a swarm of boids and wanted to know who is actually in love with whom!"}]}]}],"thread_ts":"1615209954.129300","parent_user_id":"U6C937ENB"},{"client_msg_id":"C5B25B3D-0EBA-4F4B-B862-B9389196FE60","type":"message","text":"My boids, based on that dance, are actually not the best. It relies on some global information like knowledge of all boids to randomly select friends and enemies from ","user":"U90JR0C80","ts":"1615237485.200200","team":"T68168MUP","blocks":[{"type":"rich_text","block_id":"GjI","elements":[{"type":"rich_text_section","elements":[{"type":"text","text":"My boids, based on that dance, are actually not the best. It relies on some global information like knowledge of all boids to randomly select friends and enemies from "}]}]}],"thread_ts":"1615209954.129300","parent_user_id":"U6C937ENB"},{"client_msg_id":"698a637d-bb87-4a2e-87f2-06ac144172b9","type":"message","text":"&gt; Ooo <@U6C937ENB> what are you up to?\nSparse variable selection with the Sticky Zig-Zag! <https://github.com/mschauer/ZigZagBoomerang.jl>\n\n<https://arxiv.org/abs/2103.08478> section “5.3 Learning networks of stochastic differential equations” picks up the _boid_ example as SDE and estimates who is in love with whom.","user":"U6C937ENB","ts":"1615876449.007700","team":"T68168MUP","attachments":[{"service_name":"arXiv.org","title":"Sticky PDMP samplers for sparse and local inference problems","title_link":"https://arxiv.org/abs/2103.08478","text":"We construct a new class of efficient Monte Carlo methods based on continuous-time piecewise deterministic Markov processes (PDMP) suitable for inference in high dimensional sparse models, i.e....","fallback":"arXiv.org: Sticky PDMP samplers for sparse and local inference problems","from_url":"https://arxiv.org/abs/2103.08478","service_icon":"https://static.arxiv.org/static/browse/0.3.2.6/images/icons/favicon.ico","id":1,"original_url":"https://arxiv.org/abs/2103.08478"}],"blocks":[{"type":"rich_text","block_id":"DwUTO","elements":[{"type":"rich_text_quote","elements":[{"type":"text","text":"Ooo "},{"type":"user","user_id":"U6C937ENB"},{"type":"text","text":" what are you up to?"}]},{"type":"rich_text_section","elements":[{"type":"text","text":"Sparse variable selection with the Sticky Zig-Zag! "},{"type":"link","url":"https://github.com/mschauer/ZigZagBoomerang.jl"},{"type":"text","text":"\n\n"},{"type":"link","url":"https://arxiv.org/abs/2103.08478"},{"type":"text","text":" section “5.3 Learning networks of stochastic differential equations” picks up the "},{"type":"text","text":"boid","style":{"italic":true}},{"type":"text","text":" example as SDE and estimates who is in love with whom."}]}]}],"thread_ts":"1615209954.129300","parent_user_id":"U6C937ENB","reactions":[{"name":"heart","users":["U90JR0C80"],"count":1}]}]