[{"client_msg_id":"1ccc699b-1bb6-4192-99eb-097471b650d8","type":"message","text":"From the OSF preregistration: \"If you plan on transforming, centering, recoding the data, or requiring a coding scheme for categorical variables, please describe that process.\". Given that 80% of the time of a typical non-trivial machine learning workflow is spent on data wrangling (and not tuning models), I wonder how OSF is planning that people answer this question. Maybe, an answer could look like \"See line 100-840 of src/cleaning.jl and line 600-1010 of src/aggregation.jl\".","user":"U01BTNDCUBX","ts":"1613043676.122200","team":"T68168MUP","blocks":[{"type":"rich_text","block_id":"QEUv","elements":[{"type":"rich_text_section","elements":[{"type":"text","text":"From the OSF preregistration: \"If you plan on transforming, centering, recoding the data, or requiring a coding scheme for categorical variables, please describe that process.\". Given that 80% of the time of a typical non-trivial machine learning workflow is spent on data wrangling (and not tuning models), I wonder how OSF is planning that people answer this question. Maybe, an answer could look like \"See line 100-840 of src/cleaning.jl and line 600-1010 of src/aggregation.jl\"."}]}]}],"thread_ts":"1613043676.122200","reply_count":3,"reply_users_count":3,"latest_reply":"1613074155.123300","reply_users":["U6CJRSR63","U01BTNDCUBX","U69L6CPJN"],"subscribed":false,"reactions":[{"name":"joy","users":["UUTEK2XTM","UPQP0RWTH"],"count":2}]},{"client_msg_id":"810fb068-e5d9-43fc-a0d3-544dc360204c","type":"message","text":"Maybe it's a good thing to be forced to explain 700 lines of data cleaning :slightly_smiling_face:","user":"U6CJRSR63","ts":"1613055165.122600","team":"T68168MUP","blocks":[{"type":"rich_text","block_id":"wOpE","elements":[{"type":"rich_text_section","elements":[{"type":"text","text":"Maybe it's a good thing to be forced to explain 700 lines of data cleaning "},{"type":"emoji","name":"slightly_smiling_face"}]}]}],"thread_ts":"1613043676.122200","parent_user_id":"U01BTNDCUBX","reactions":[{"name":"point_up","users":["UBF9YRB6H","U8JP5B9T2"],"count":2},{"name":"100","users":["U8JP5B9T2"],"count":1}]},{"client_msg_id":"06f60b29-cb2c-40d1-a9f2-58ed9b5b22e9","type":"message","text":"Fair enough. Maybe it should be interpreted as \"try to be as complete as reasonably possible\".","user":"U01BTNDCUBX","ts":"1613059326.123000","team":"T68168MUP","blocks":[{"type":"rich_text","block_id":"r50gL","elements":[{"type":"rich_text_section","elements":[{"type":"text","text":"Fair enough. Maybe it should be interpreted as \"try to be as complete as reasonably possible\"."}]}]}],"thread_ts":"1613043676.122200","parent_user_id":"U01BTNDCUBX"},{"client_msg_id":"9aab7c53-4c6f-473e-8217-5a86e7a52218","type":"message","text":"From my understanding of preregistration \"we will run this script to do the data preparation\" and linking to the script is the ideal statement of a data preparation process.","user":"U69L6CPJN","ts":"1613074155.123300","team":"T68168MUP","blocks":[{"type":"rich_text","block_id":"IcZC","elements":[{"type":"rich_text_section","elements":[{"type":"text","text":"From my understanding of preregistration \"we will run this script to do the data preparation\" and linking to the script is the ideal statement of a data preparation process."}]}]}],"thread_ts":"1613043676.122200","parent_user_id":"U01BTNDCUBX"}]