[{"client_msg_id":"89a062f0-7d6d-482f-9b8e-609ff77f932a","type":"message","text":"Gatekeepers, all of you! Booooooo!","user":"U6QGE7S86","ts":"1617749980.077100","team":"T68168MUP","blocks":[{"type":"rich_text","block_id":"rQbsy","elements":[{"type":"rich_text_section","elements":[{"type":"text","text":"Gatekeepers, all of you! Booooooo!"}]}]}],"thread_ts":"1617749980.077100","reply_count":6,"reply_users_count":3,"latest_reply":"1617751428.078900","reply_users":["UPUBAM63X","U6QGE7S86","U0138UTB7A4"],"is_locked":false,"subscribed":false,"reactions":[{"name":"phparrot","users":["UGU761DU2","UPUBAM63X"],"count":2}]},{"client_msg_id":"bf89b2c8-6bb1-489a-8602-9005f29f9e1f","type":"message","text":"Gatekeeping is telling someone to write their ray tracer/genetic algorithm/etc in Excel. Gate opening is telling someone they shouldn't do that unless they want to make a meme.","user":"UPUBAM63X","ts":"1617750344.077300","team":"T68168MUP","edited":{"user":"UPUBAM63X","ts":"1617750377.000000"},"blocks":[{"type":"rich_text","block_id":"TRv","elements":[{"type":"rich_text_section","elements":[{"type":"text","text":"Gatekeeping is telling someone to write their ray tracer/genetic algorithm/etc in Excel. Gate opening is telling someone they shouldn't do that unless they want to make a meme."}]}]}],"thread_ts":"1617749980.077100","parent_user_id":"U6QGE7S86"},{"bot_id":"BUQUB8RBN","type":"message","text":"boooooo","user":"U6QGE7S86","ts":"1617750401.077900","team":"T68168MUP","bot_profile":{"id":"BUQUB8RBN","deleted":false,"name":"giphy","updated":1583162249,"app_id":"A0F827J2C","icons":{"image_36":"https://a.slack-edge.com/dc483/img/plugins/giphy/service_72.png","image_48":"https://a.slack-edge.com/dc483/img/plugins/giphy/service_48.png","image_72":"https://a.slack-edge.com/dc483/img/plugins/giphy/service_72.png"},"team_id":"T68168MUP"},"blocks":[{"type":"image","block_id":"Tz2n","image_url":"https://media2.giphy.com/media/h7RjBiUcyjBuwqzpSt/giphy.gif?cid=6104955eb1183029d41101f010a2e085d76818bd34933b42&rid=giphy.gif&ct=g","alt_text":"boooooo","title":{"type":"plain_text","text":"boooooo","emoji":true},"fallback":"500x349px image","image_width":500,"image_height":349,"image_bytes":624173,"is_animated":true},{"type":"context","block_id":"bLd","elements":[{"type":"image","image_url":"https://a.slack-edge.com/dc483/img/plugins/giphy/service_32.png","alt_text":"giphy logo"},{"type":"mrkdwn","text":"Posted using /giphy | GIF by <https://giphy.com/theringer/|The Ringer>","verbatim":false}]}],"thread_ts":"1617749980.077100","parent_user_id":"U6QGE7S86","reactions":[{"name":"rolling_on_the_floor_laughing","users":["UPUBAM63X"],"count":1}]},{"client_msg_id":"f476f15e-7227-4c9f-8224-79e1c29b8614","type":"message","text":"Asking for a friend, is there a way to convert LLVM representation into Excel code?","user":"U0138UTB7A4","ts":"1617750999.078200","team":"T68168MUP","blocks":[{"type":"rich_text","block_id":"a47","elements":[{"type":"rich_text_section","elements":[{"type":"text","text":"Asking for a friend, is there a way to convert LLVM representation into Excel code?"}]}]}],"thread_ts":"1617749980.077100","parent_user_id":"U6QGE7S86"},{"client_msg_id":"124ec7ca-8404-4e09-bdbf-9176ada2eab3","type":"message","text":"Yes, it is possible.","user":"U6QGE7S86","ts":"1617751128.078400","team":"T68168MUP","blocks":[{"type":"rich_text","block_id":"ZtX3","elements":[{"type":"rich_text_section","elements":[{"type":"text","text":"Yes, it is possible."}]}]}],"thread_ts":"1617749980.077100","parent_user_id":"U6QGE7S86"},{"client_msg_id":"40cbeb28-7836-4565-8465-d5962be7e2d5","type":"message","text":"I would like to relay back the message from my friend! They said thanks and they were curious as to how hmm EDIT: any suggestions welcome on resources ;)","user":"U0138UTB7A4","ts":"1617751183.078600","team":"T68168MUP","edited":{"user":"U0138UTB7A4","ts":"1617751237.000000"},"blocks":[{"type":"rich_text","block_id":"DnI","elements":[{"type":"rich_text_section","elements":[{"type":"text","text":"I would like to relay back the message from my friend! They said thanks and they were curious as to how hmm EDIT: any suggestions welcome on resources ;)"}]}]}],"thread_ts":"1617749980.077100","parent_user_id":"U6QGE7S86"},{"client_msg_id":"1e5c924c-78e1-4156-beff-b2a21b03cbe0","type":"message","text":"Wow thats so weird to think about... Converting all of a script like SciML into LLVM, and then converting it all to Excel, then running it","user":"U0138UTB7A4","ts":"1617751428.078900","team":"T68168MUP","edited":{"user":"U0138UTB7A4","ts":"1617751458.000000"},"blocks":[{"type":"rich_text","block_id":"fDl","elements":[{"type":"rich_text_section","elements":[{"type":"text","text":"Wow thats so weird to think about... Converting all of a script like SciML into LLVM, and then converting it all to Excel, then running it"}]}]}],"thread_ts":"1617749980.077100","parent_user_id":"U6QGE7S86"}]