{"id":"U01PKB8QDS5","team_id":"T68168MUP","name":"mahdi.mirhoseini","deleted":false,"color":"e0a729","real_name":"Mahdi Mirhosseini","tz":"America/New_York","tz_label":"Eastern Standard Time","tz_offset":-18000,"profile":{"title":"","phone":"","skype":"","real_name":"Mahdi Mirhosseini","real_name_normalized":"Mahdi Mirhosseini","display_name":"MahdiMir","display_name_normalized":"MahdiMir","fields":[],"status_text":"","status_emoji":"","status_expiration":0,"avatar_hash":"592b96939ebc","image_original":"https://avatars.slack-edge.com/2021-02-24/1785703925429_592b96939ebc0ade411c_original.jpg","is_custom_image":true,"first_name":"Mahdi","last_name":"Mirhosseini","image_24":"https://avatars.slack-edge.com/2021-02-24/1785703925429_592b96939ebc0ade411c_24.jpg","image_32":"https://avatars.slack-edge.com/2021-02-24/1785703925429_592b96939ebc0ade411c_32.jpg","image_48":"https://avatars.slack-edge.com/2021-02-24/1785703925429_592b96939ebc0ade411c_48.jpg","image_72":"https://avatars.slack-edge.com/2021-02-24/1785703925429_592b96939ebc0ade411c_72.jpg","image_192":"https://avatars.slack-edge.com/2021-02-24/1785703925429_592b96939ebc0ade411c_192.jpg","image_512":"https://avatars.slack-edge.com/2021-02-24/1785703925429_592b96939ebc0ade411c_512.jpg","image_1024":"https://avatars.slack-edge.com/2021-02-24/1785703925429_592b96939ebc0ade411c_1024.jpg","status_text_canonical":"","team":"T68168MUP"},"is_admin":false,"is_owner":false,"is_primary_owner":false,"is_restricted":false,"is_ultra_restricted":false,"is_bot":false,"is_app_user":false,"updated":1614176092,"is_email_confirmed":true}